{
    "name": "endpoint-name",
    "description": "Short description of what this endpoint does",
    "method": "POST",
    "url": {
        "protocol": "https",
        "host": "api.example.com"
    },
    "headers": [
        {
            "name": "Content-Type",
            "value": "application/json"
        },
        {
            "name": "Authorization",
            "value": "Bearer {token}"
        },
        {
            "name": "DeviceId",
            "value": "{deviceId}"
        }
    ],
    "request": {
        "type": "object",
        "schema": [
            {
                "name": "username",
                "type": "string",
                "default": null,
                "description": "username",
                "required": true
            },
            {
                "name": "password",
                "type": "string",
                "default": null,
                "description": "user password",
                "required": true
            },
            {
                "name": "data",
                "type": "object",
                "default": null,
                "description": "",
                "required": false
            }
        ],
        "example": {
            "username": "user001",
            "password": "secret123A@"
        }
    },
    "responses": [
        {
            "code": 200,
            "description": "Successful response",
            "type": "object",
            "schema": [
                {
                    "name": "message",
                    "type": "string",
                    "default": null,
                    "description": "Human-readable message",
                    "required": true
                },
                {
                    "name": "data",
                    "type": "object",
                    "default": null,
                    "description": "Response payload",
                    "required": false
                }
            ],
            "example": {
                "status": 200,
                "message": "OK",
                "data": null
            }
        },
        {
            "code": 400,
            "description": "Bad request",
            "type": "object",
            "schema": [
                {
                    "name": "status",
                    "type": "int",
                    "default": "200",
                    "description": "Status code",
                    "required": true
                },
                {
                    "name": "message",
                    "type": "string",
                    "default": null,
                    "description": "Human-readable message",
                    "required": true
                },
                {
                    "name": "data",
                    "type": "object",
                    "default": null,
                    "description": "Response payload",
                    "required": false
                }
            ]
        }
    ]
}